ai_fix/__init__.py
ai_fix_dev-0.1.0.dist-info/METADATA
ai_fix_dev-0.1.0.dist-info/WHEEL
ai_fix_dev-0.1.0.dist-info/RECORD
