Metadata-Version: 2.4
Name: ai-fix-dev
Version: 0.1.0
Summary: Library of post-processing helpers to fix AI output errors
Author: Korakot Chaovavanich
License: MIT
Keywords: ai,postprocess,segmentation
Requires-Python: >=3.9
